codex/__init__.py
codex/_base_client.py
codex/_client.py
codex/_compat.py
codex/_constants.py
codex/_exceptions.py
codex/_files.py
codex/_models.py
codex/_qs.py
codex/_resource.py
codex/_response.py
codex/_streaming.py
codex/_types.py
codex/_version.py
codex/pagination.py
codex/py.typed
codex/_utils/__init__.py
codex/_utils/_compat.py
codex/_utils/_datetime_parse.py
codex/_utils/_logs.py
codex/_utils/_proxy.py
codex/_utils/_reflection.py
codex/_utils/_resources_proxy.py
codex/_utils/_streams.py
codex/_utils/_sync.py
codex/_utils/_transform.py
codex/_utils/_typing.py
codex/_utils/_utils.py
codex/lib/.keep
codex/resources/__init__.py
codex/resources/health.py
codex/resources/organizations/__init__.py
codex/resources/organizations/organizations.py
codex/resources/organizations/billing/__init__.py
codex/resources/organizations/billing/billing.py
codex/resources/organizations/billing/card_details.py
codex/resources/organizations/billing/plan_details.py
codex/resources/organizations/billing/setup_intent.py
codex/resources/projects/__init__.py
codex/resources/projects/access_keys.py
codex/resources/projects/evals.py
codex/resources/projects/projects.py
codex/resources/projects/query_logs.py
codex/resources/projects/remediations.py
codex/resources/users/__init__.py
codex/resources/users/users.py
codex/resources/users/verification.py
codex/resources/users/myself/__init__.py
codex/resources/users/myself/api_key.py
codex/resources/users/myself/myself.py
codex/resources/users/myself/organizations.py
codex/types/__init__.py
codex/types/health_check_response.py
codex/types/organization_list_members_response.py
codex/types/organization_retrieve_permissions_response.py
codex/types/organization_schema_public.py
codex/types/project_create_from_template_params.py
codex/types/project_create_params.py
codex/types/project_detect_params.py
codex/types/project_detect_response.py
codex/types/project_invite_sme_params.py
codex/types/project_invite_sme_response.py
codex_sdk-0.1.0a32.dist-info/METADATA
codex_sdk-0.1.0a32.dist-info/WHEEL
codex_sdk-0.1.0a32.dist-info/licenses/LICENSE
codex_sdk-0.1.0a32.dist-info/RECORD
