Metadata-Version: 2.3
Name: codex-sdk
Version: 0.1.0a32
Summary: Internal SDK used within cleanlab-codex package. Refer to https://pypi.org/project/cleanlab-codex/ instead.
Project-URL: Homepage, https://github.com/cleanlab/codex-python
Project-URL: Repository, https://github.com/cleanlab/codex-python
Author-email: Cleanlab <team@cleanlab.ai>
License: MIT
Classifier: Intended Audience :: Developers
Classifier: License :: OSI Approved :: MIT License
Classifier: Operating System :: MacOS
Classifier: Operating System :: Microsoft :: Windows
Classifier: Operating System :: OS Independent
Classifier: Operating System :: POSIX
Classifier: Operating System :: POSIX :: Linux
Classifier: Programming Language :: Python :: 3.8
Classifier: Programming Language :: Python :: 3.9
Classifier: Programming Language :: Python :: 3.10
Classifier: Programming Language :: Python :: 3.11
Classifier: Programming Language :: Python :: 3.12
Classifier: Programming Language :: Python :: 3.13
Classifier: Topic :: Software Development :: Libraries :: Python Modules
Classifier: Typing :: Typed
Requires-Python: >=3.8
Requires-Dist: anyio<5,>=3.5.0
Requires-Dist: distro<2,>=1.7.0
Requires-Dist: httpx<1,>=0.23.0
Requires-Dist: pydantic<3,>=1.9.0
Requires-Dist: sniffio
Requires-Dist: typing-extensions<5,>=4.10
Provides-Extra: aiohttp
Requires-Dist: aiohttp; extra == 'aiohttp'
Requires-Dist: httpx-aiohttp>=0.1.9; extra == 'aiohttp'
